LICENSE
README.md
setup.py
PRISM/__init__.py
PRISM/bounds/betting_bounds.py
PRISM/models/AbstractModels.py
PRISM/models/GPTModels.py
PRISM/process/PRISM_A.py
PRISM/process/PRISM_P.py
PRISM/process/PRISM_R.py
PRISM/sampler/wor_sampler.py
ai_prism.egg-info/PKG-INFO
ai_prism.egg-info/SOURCES.txt
ai_prism.egg-info/dependency_links.txt
ai_prism.egg-info/requires.txt
ai_prism.egg-info/top_level.txt